CHANGELOG.md
LICENSE
README.md
nv/utils/collections/registry/__init__.py
nv/utils/collections/registry/core.py
nv/utils/collections/registry/implementations/__init__.py
nv/utils/collections/registry/implementations/string.py
nv/utils/collections/registry/py.typed
nv/utils/collections/registry/types.py
nv/utils/collections/registry/typing.py
nv_utils_registry-0.1.0.dist-info/LICENSE
nv_utils_registry-0.1.0.dist-info/WHEEL
nv_utils_registry-0.1.0.dist-info/METADATA
nv_utils_registry-0.1.0.dist-info/RECORD
