Metadata-Version: 2.1
Name: nv-utils-registry
Version: 0.1.0
Summary: Specialized mapping for retrieving content with default hirearchy of matching keys
Home-page: https://github.com/nextventures/nv-utils-registry.git
License: MIT
Author: Gustavo Santos
Author-email: gustavo@next.ventures
Requires-Python: >=3.10,<4.0
Classifier: Development Status :: 4 - Beta
Classifier: Intended Audience :: Developers
Classifier: License :: OSI Approved :: MIT License
Classifier: Natural Language :: English
Classifier: Operating System :: OS Independent
Classifier: Programming Language :: Python :: 3
Classifier: Programming Language :: Python :: 3.10
Classifier: Topic :: Software Development :: Libraries :: Python Modules
Classifier: Typing :: Typed
Project-URL: Repository, https://github.com/nextventures/nv-utils-registry.git
